{
    "photoset": "72157633699136668",
    "subtitle": "Joint Service Open House",
    "breadcrumbs": [
        {
            "name": "home",
            "url": "/photography/"
        },
        {
            "name": "events",
            "url": "/photography/events/"
        },
        {
            "name": "2012",
            "url": "/photography/events/2012/"
        },
        {
            "name": "joint service open house",
            "url": "/photography/events/2012/jsoh/"
        }
    ]
}